vapi_python/__init__.py
vapi_python/daily_call.py
vapi_python/vapi_python.py
vapi_python-0.1.8.dist-info/LICENSE
vapi_python-0.1.8.dist-info/METADATA
vapi_python-0.1.8.dist-info/WHEEL
vapi_python-0.1.8.dist-info/entry_points.txt
vapi_python-0.1.8.dist-info/top_level.txt
vapi_python-0.1.8.dist-info/RECORD
