Metadata-Version: 2.1
Name: vapi-python
Version: 0.1.8
Summary: This package lets you start Vapi calls directly from Python.
Home-page: https://github.com/jordan.cde/vapi_python
Author: Vapi AI
Author-email: team@vapi.ai
License: MIT license
Keywords: vapi_python
Classifier: Development Status :: 2 - Pre-Alpha
Classifier: Intended Audience :: Developers
Classifier: License :: OSI Approved :: MIT License
Classifier: Natural Language :: English
Classifier: Programming Language :: Python :: 3
Classifier: Programming Language :: Python :: 3.6
Classifier: Programming Language :: Python :: 3.7
Classifier: Programming Language :: Python :: 3.8
Requires-Python: >=3.6
License-File: LICENSE
Requires-Dist: daily-python
Requires-Dist: pyaudio
